{
  "generator-jhipster": {
    "applicationType": "monolith",
    "gitHubOrganization": "nassahmed",
    "baseName": "jhipsterSampleApplication",
    "packageName": "io.github.jhipster.application",
    "serverPort": 8080,
    "serviceDiscoveryType": false,
    "authenticationType": "jwt",
    "uaaBaseName": "../uaa",
    "hibernateCache": "ehcache",
    "clusteredHttpSession": false,
    "websocket": false,
    "databaseType": "sql",
    "devDatabaseType": "h2Disk",
    "prodDatabaseType": "mysql",
    "searchEngine": false,
    "enableSwaggerCodegen": false,
    "messageBroker": false,
    "buildTool": "maven",
    "enableSocialSignIn": false,
    "useSass": false,
    "clientPackageManager": "yarn",
    "testFrameworks": [],
    "enableTranslation": false,
    "nativeLanguage": "en",
    "languages": [
      "en"
    ],
    "clientFramework": "angularX",
    "jhipsterVersion": "4.8.1",
    "packageFolder": "io/github/jhipster/application",
    "jwtSecretKey": "8d9caa4161fe2985f7a376c9fa571f6d30a6e1bb",
    "jhiPrefix": "jhi"
  }
}